anvargamodule/__init__.py
anvargamodule/add.py
anvargamodule/substract.py
anvargamodule/extras/__init__.py
anvargamodule/extras/divide.py
anvargamodule/extras/multiply.py
anvargamodule-0.0.1.dist-info/DESCRIPTION.rst
anvargamodule-0.0.1.dist-info/METADATA
anvargamodule-0.0.1.dist-info/RECORD
anvargamodule-0.0.1.dist-info/WHEEL
anvargamodule-0.0.1.dist-info/metadata.json
anvargamodule-0.0.1.dist-info/top_level.txt
