Metadata-Version: 2.0
Name: anvargamodule
Version: 0.0.1
Summary: anvarga package
Home-page: UNKNOWN
Author: Tony Vargas
Author-email: tontvt94@gmail.com
License: UNKNOWN
Keywords: python,first package
Platform: UNKNOWN
Classifier: Development Status :: 3 - Alpha
Classifier: Intended Audience :: Education
Classifier: Programming Language :: Python :: 2
Classifier: Programming Language :: Python :: 3
Classifier: Operating System :: MacOS :: MacOS X
Classifier: Operating System :: Microsoft :: Windows
